hack_assemble/__init__.py
hack_assemble/__main__.py
hack_assemble/assemble.py
hack_assemble/code.py
hack_assemble/parser.py
hack_assemble/utils.py
hack_assemble-0.1.dist-info/DESCRIPTION.rst
hack_assemble-0.1.dist-info/METADATA
hack_assemble-0.1.dist-info/RECORD
hack_assemble-0.1.dist-info/WHEEL
hack_assemble-0.1.dist-info/entry_points.txt
hack_assemble-0.1.dist-info/metadata.json
hack_assemble-0.1.dist-info/top_level.txt
hack_assembler/__init__.py
hack_assembler/__main__.py
hack_assembler/assemble.py
hack_assembler/code.py
hack_assembler/parser.py
hack_assembler/utils.py
